{"cameraMode":{"drawMode":0,"name":"Shaded","section":"Shading Mode"},"sceneLighting":true,"audioPlay":false,"sceneViewState":{"showFog":true,"showMaterialUpdate":false,"showSkybox":true,"showFlares":true,"showImageEffects":true,"showParticleSystems":true},"in2DMode":false,"pivot":{"x":-1.169845700263977,"y":1.5504871606826783,"z":1.236291766166687},"rotation":{"x":-0.21855776011943818,"y":0.06347234547138214,"z":-0.014247492887079716,"w":-0.9736621379852295},"size":11.995550155639649,"orthographic":false}